fuzzymerge_parallel/FuzzyMergeParallel.py
fuzzymerge_parallel/__init__.py
fuzzymerge_parallel/aux.py
fuzzymerge_parallel/matches_dask.py
fuzzymerge_parallel/matches_multiproc.py
fuzzymerge_parallel-1.0.0.dist-info/AUTHORS.rst
fuzzymerge_parallel-1.0.0.dist-info/LICENSE
fuzzymerge_parallel-1.0.0.dist-info/METADATA
fuzzymerge_parallel-1.0.0.dist-info/WHEEL
fuzzymerge_parallel-1.0.0.dist-info/entry_points.txt
fuzzymerge_parallel-1.0.0.dist-info/top_level.txt
fuzzymerge_parallel-1.0.0.dist-info/RECORD
