Metadata-Version: 2.1
Name: fuzzymerge-parallel
Version: 1.0.0
Summary: FuzzyMergeParallel is a Python package that enables efficient fuzzy merging of two dataframes based on string columns. With FuzzyMergeParallel, users can easily merge datasets, benefitting from enhanced performance through parallel computing with multiprocessing and Dask.
Home-page: https://github.com/ULHPC/fuzzymerge_parallel
Author: Oscar J. Castro-Lopez
Author-email: oscar.castro@uni.lu
License: MIT license
Keywords: fuzzymerge_parallel
Classifier: Development Status :: 2 - Pre-Alpha
Classifier: Intended Audience :: Developers
Classifier: License :: OSI Approved :: MIT License
Classifier: Natural Language :: English
Classifier: Programming Language :: Python :: 3
Classifier: Programming Language :: Python :: 3.6
Classifier: Programming Language :: Python :: 3.7
Classifier: Programming Language :: Python :: 3.8
Classifier: Programming Language :: Python :: 3.9
Classifier: Programming Language :: Python :: 3.10
Classifier: Programming Language :: Python :: 3.11
Requires-Python: >=3.6
License-File: LICENSE
License-File: AUTHORS.rst
Requires-Dist: Click >=7.0
Requires-Dist: Levenshtein >=0.21.0
Requires-Dist: nltk >=3.8.1
Requires-Dist: numpy >=1.23.5
Requires-Dist: pandas >=1.5.3
Requires-Dist: tqdm >=4.65.0
Requires-Dist: psutil ==5.9.5
Provides-Extra: dask
Requires-Dist: dask[distributed] >=2023.5.0 ; extra == 'dask'
